{
  "campaigns": [
    {
      "id": 1,
      "name": "봄 시즌 캠페인",
      "start_date": "2024-03-01",
      "end_date": "2024-05-31",
      "budget": 5000000,
      "impressions": 2500000,
      "clicks": 125000,
      "conversions": 3750,
      "revenue": 18750000
    },
    {
      "id": 2,
      "name": "여름 프로모션",
      "start_date": "2024-06-01",
      "end_date": "2024-08-31",
      "budget": 7000000,
      "impressions": 3500000,
      "clicks": 175000,
      "conversions": 5250,
      "revenue": 26250000
    }
  ]
}