{
  "keywords": [
    {
      "keyword": "디지털 마케팅",
      "funnel": "인지",
      "month": "2024-01",
      "aim_score": 75,
      "search_volume": 5200,
      "trend": "상승"
    },
    {
      "keyword": "SEO 최적화",
      "funnel": "탐색",
      "month": "2024-01",
      "aim_score": 68,
      "search_volume": 3400,
      "trend": "안정"
    },
    {
      "keyword": "소셜 미디어 전략",
      "funnel": "의도",
      "month": "2024-01",
      "aim_score": 82,
      "search_volume": 2800,
      "trend": "상승"
    },
    {
      "keyword": "콘텐츠 마케팅",
      "funnel": "유입",
      "month": "2024-01",
      "aim_score": 71,
      "search_volume": 4100,
      "trend": "안정"
    },
    {
      "keyword": "바이럴 마케팅",
      "funnel": "확산",
      "month": "2024-01",
      "aim_score": 79,
      "search_volume": 3600,
      "trend": "상승"
    },
    {
      "keyword": "AI 마케팅",
      "funnel": "인지",
      "month": "2024-02",
      "aim_score": 85,
      "search_volume": 6200,
      "trend": "상승"
    },
    {
      "keyword": "고객 분석",
      "funnel": "탐색",
      "month": "2024-02",
      "aim_score": 72,
      "search_volume": 3800,
      "trend": "상승"
    },
    {
      "keyword": "전환율 최적화",
      "funnel": "의도",
      "month": "2024-02",
      "aim_score": 88,
      "search_volume": 3200,
      "trend": "상승"
    },
    {
      "keyword": "이메일 마케팅",
      "funnel": "유입",
      "month": "2024-02",
      "aim_score": 76,
      "search_volume": 4500,
      "trend": "안정"
    },
    {
      "keyword": "인플루언서 마케팅",
      "funnel": "확산",
      "month": "2024-02",
      "aim_score": 84,
      "search_volume": 4200,
      "trend": "상승"
    },
    {
      "keyword": "마케팅 자동화",
      "funnel": "인지",
      "month": "2024-03",
      "aim_score": 79,
      "search_volume": 5500,
      "trend": "상승"
    },
    {
      "keyword": "데이터 기반 마케팅",
      "funnel": "탐색",
      "month": "2024-03",
      "aim_score": 81,
      "search_volume": 4100,
      "trend": "상승"
    },
    {
      "keyword": "고객 경험 최적화",
      "funnel": "의도",
      "month": "2024-03",
      "aim_score": 89,
      "search_volume": 3500,
      "trend": "상승"
    },
    {
      "keyword": "모바일 마케팅",
      "funnel": "유입",
      "month": "2024-03",
      "aim_score": 80,
      "search_volume": 4800,
      "trend": "상승"
    },
    {
      "keyword": "소셜 커머스",
      "funnel": "확산",
      "month": "2024-03",
      "aim_score": 87,
      "search_volume": 4600,
      "trend": "상승"
    }
  ]
}